me_cli/__init__.py
me_cli/cli.py
me_cli-0.0.3.dist-info/METADATA
me_cli-0.0.3.dist-info/WHEEL
me_cli-0.0.3.dist-info/entry_points.txt
me_cli-0.0.3.dist-info/top_level.txt
me_cli-0.0.3.dist-info/RECORD
